Metadata-Version: 2.1
Name: torch-basic-models
Version: 0.2.5.post2
Summary: Basic Models for PyTorch, with Unified Interface
Home-page: https://github.com/FebruaryBreeze/torch-basic-models
Author: SF-Zhou
Author-email: sfzhou.scut@gmail.com
License: MIT
Keywords: PyTorch Basic Models
Platform: UNKNOWN
Requires-Python: >=3.6.0
